gc100.py
python_gc100-1.0.3a0.dist-info/DESCRIPTION.rst
python_gc100-1.0.3a0.dist-info/METADATA
python_gc100-1.0.3a0.dist-info/RECORD
python_gc100-1.0.3a0.dist-info/WHEEL
python_gc100-1.0.3a0.dist-info/metadata.json
python_gc100-1.0.3a0.dist-info/top_level.txt
