Metadata-Version: 2.0
Name: python-gc100
Version: 1.0.3a0
Summary: A Python-based socket client for
Home-page: https://github.com/davegravy/python-gc100
Author: David Grant
Author-email: davegravy@gmail.com
License: GPLv3
Keywords: development gc100 home-automation
Platform: UNKNOWN
Classifier: Development Status :: 3 - Alpha
Classifier: Intended Audience :: Developers
Classifier: Topic :: Home Automation
Classifier: License :: OSI Approved :: GNU General Public License v3 (GPLv3)
Classifier: Programming Language :: Python :: 3.3
Classifier: Programming Language :: Python :: 3.4
Classifier: Programming Language :: Python :: 3.5
Provides-Extra: dev
Requires-Dist: check-manifest; extra == 'dev'
Provides-Extra: test
Requires-Dist: coverage; extra == 'test'
